pykron/__init__.py
pykron/core.py
pykron-0.13.dist-info/DESCRIPTION.rst
pykron-0.13.dist-info/METADATA
pykron-0.13.dist-info/RECORD
pykron-0.13.dist-info/WHEEL
pykron-0.13.dist-info/metadata.json
pykron-0.13.dist-info/top_level.txt
