Metadata-Version: 2.0
Name: pykron
Version: 0.13
Summary: Python module for managing asynchronous tasks
Home-page: https://github.com/s4hri/pykron
Author: Davide De Tommaso
Author-email: dtmdvd@gmail.com
License: UNKNOWN
Download-URL: https://github.com/s4hri/pykron/archive/0.13.tar.gz
Keywords: multithreading
Platform: UNKNOWN
Classifier: Programming Language :: Python :: 3.5
Classifier: Programming Language :: Python :: 3.6
Classifier: Programming Language :: Python :: 3.7
Classifier: Programming Language :: Python :: 3.8
Requires-Dist: pandas (==1.0.3)
